CMakeLists.txt
LICENSE
MANIFEST.in
README.md
pyproject.toml
setup.py
cmake/FindNetCDF.cmake
cmake/knownHosts.cmake
externalPackages/installDoctest.sh
externalPackages/doctest/doctest.h
externalPackages/eigen/Eigen/Cholesky
externalPackages/eigen/Eigen/CholmodSupport
externalPackages/eigen/Eigen/Core
externalPackages/eigen/Eigen/Dense
externalPackages/eigen/Eigen/Eigen
externalPackages/eigen/Eigen/Eigenvalues
externalPackages/eigen/Eigen/Geometry
externalPackages/eigen/Eigen/Householder
externalPackages/eigen/Eigen/IterativeLinearSolvers
externalPackages/eigen/Eigen/Jacobi
externalPackages/eigen/Eigen/KLUSupport
externalPackages/eigen/Eigen/LU
externalPackages/eigen/Eigen/MetisSupport
externalPackages/eigen/Eigen/OrderingMethods
externalPackages/eigen/Eigen/PaStiXSupport
externalPackages/eigen/Eigen/PardisoSupport
externalPackages/eigen/Eigen/QR
externalPackages/eigen/Eigen/QtAlignedMalloc
externalPackages/eigen/Eigen/SPQRSupport
externalPackages/eigen/Eigen/SVD
externalPackages/eigen/Eigen/Sparse
externalPackages/eigen/Eigen/SparseCholesky
externalPackages/eigen/Eigen/SparseCore
externalPackages/eigen/Eigen/SparseLU
externalPackages/eigen/Eigen/SparseQR
externalPackages/eigen/Eigen/StdDeque
externalPackages/eigen/Eigen/StdList
externalPackages/eigen/Eigen/StdVector
externalPackages/eigen/Eigen/SuperLUSupport
externalPackages/eigen/Eigen/UmfPackSupport
externalPackages/eigen/Eigen/src/Cholesky/LDLT.h
externalPackages/eigen/Eigen/src/Cholesky/LLT.h
externalPackages/eigen/Eigen/src/Cholesky/LLT_LAPACKE.h
externalPackages/eigen/Eigen/src/CholmodSupport/CholmodSupport.h
externalPackages/eigen/Eigen/src/Core/ArithmeticSequence.h
externalPackages/eigen/Eigen/src/Core/Array.h
externalPackages/eigen/Eigen/src/Core/ArrayBase.h
externalPackages/eigen/Eigen/src/Core/ArrayWrapper.h
externalPackages/eigen/Eigen/src/Core/Assign.h
externalPackages/eigen/Eigen/src/Core/AssignEvaluator.h
externalPackages/eigen/Eigen/src/Core/Assign_MKL.h
src/booz_xform.egg-info/PKG-INFO
src/booz_xform.egg-info/SOURCES.txt
src/booz_xform.egg-info/dependency_links.txt
src/booz_xform.egg-info/not-zip-safe
src/booz_xform.egg-info/requires.txt
src/booz_xform.egg-info/top_level.txt
