Metadata-Version: 1.0
Name: booz-xform
Version: 0.0.9
Summary: Transformation to Boozer coordinates
Home-page: UNKNOWN
Author: Matt Landreman
Author-email: matt.landreman@gmail.com
License: UNKNOWN
Platform: UNKNOWN
